dm4/__init__.py
dm4/__main__.py
dm4/dm4file.py
dm4/headers.py
dm4/helpers.py
dm4-1.0.3.dist-info/licenses/LICENSE
dm4-1.0.3.dist-info/WHEEL
dm4-1.0.3.dist-info/METADATA
dm4-1.0.3.dist-info/RECORD
