Metadata-Version: 2.4
Name: dm4
Version: 1.0.3
Summary: A Digital Micrograph 4 (DM4) file reader.
Author-email: James Anderson <james.r.anderson@utah.edu>
Classifier: Programming Language :: Python :: 3
Classifier: License :: OSI Approved :: MIT License
Classifier: Operating System :: OS Independent
Classifier: Development Status :: 5 - Production/Stable
Classifier: Intended Audience :: Developers
Classifier: Intended Audience :: Science/Research
Classifier: Topic :: Software Development :: Libraries :: Python Modules
Classifier: Topic :: Scientific/Engineering :: Bio-Informatics
License-File: LICENSE
Requires-Dist: numpy ; extra == "test"
Project-URL: Home, https://github.com/nornir/dm4
Project-URL: Issues, https://github.com/nornir/dm4/issues
Provides-Extra: test
